{
  "hadm_id": 128096,
  "notes": [
    {
      "note_id": 53563,
      "category": "Discharge summary",
      "description": "Report",
      "annotations": [
        {
          "begin": 1141,
          "end": 1155,
          "code": "272.4",
          "code_system": "ICD-9-CM",
          "type": "ECAN-supervised-attention"
        },
        {
          "begin": 7116,
          "end": 7130,
          "code": "272.4",
          "code_system": "ICD-9-CM",
          "type": "ECAN-supervised-attention"
        },
        {
          "begin": 1258,
          "end": 1261,
          "code": "305.1",
          "code_system": "ICD-9-CM",
          "type": "ECAN-supervised-attention"
        },
        {
          "begin": 1370,
          "end": 1388,
          "code": "305.1",
          "code_system": "ICD-9-CM",
          "type": "ECAN-supervised-attention"
        },
        {
          "begin": 1408,
          "end": 1417,
          "code": "305.1",
          "code_system": "ICD-9-CM",
          "type": "ECAN-supervised-attention"
        },
        {
          "begin": 1510,
          "end": 1516,
          "code": "305.1",
          "code_system": "ICD-9-CM",
          "type": "ECAN-supervised-attention"
        },
        {
          "begin": 7233,
          "end": 7240,
          "code": "305.1",
          "code_system": "ICD-9-CM",
          "type": "ECAN-supervised-attention"
        },
        {
          "begin": 1141,
          "end": 1168,
          "code": "401.9",
          "code_system": "ICD-9-CM",
          "type": "ECAN-supervised-attention"
        },
        {
          "begin": 5373,
          "end": 5383,
          "code": "401.9",
          "code_system": "ICD-9-CM",
          "type": "ECAN-supervised-attention"
        },
        {
          "begin": 7116,
          "end": 7143,
          "code": "401.9",
          "code_system": "ICD-9-CM",
          "type": "ECAN-supervised-attention"
        },
        {
          "begin": 329,
          "end": 335,
          "code": "424.0",
          "code_system": "ICD-9-CM",
          "type": "ECAN-supervised-attention"
        },
        {
          "begin": 715,
          "end": 721,
          "code": "424.0",
          "code_system": "ICD-9-CM",
          "type": "ECAN-supervised-attention"
        },
        {
          "begin": 1125,
          "end": 1131,
          "code": "424.0",
          "code_system": "ICD-9-CM",
          "type": "ECAN-supervised-attention"
        },
        {
          "begin": 3034,
          "end": 3040,
          "code": "424.0",
          "code_system": "ICD-9-CM",
          "type": "ECAN-supervised-attention"
        },
        {
          "begin": 4196,
          "end": 4202,
          "code": "424.0",
          "code_system": "ICD-9-CM",
          "type": "ECAN-supervised-attention"
        },
        {
          "begin": 7100,
          "end": 7106,
          "code": "424.0",
          "code_system": "ICD-9-CM",
          "type": "ECAN-supervised-attention"
        },
        {
          "begin": 329,
          "end": 335,
          "code": "424.1",
          "code_system": "ICD-9-CM",
          "type": "ECAN-supervised-attention"
        },
        {
          "begin": 715,
          "end": 721,
          "code": "424.1",
          "code_system": "ICD-9-CM",
          "type": "ECAN-supervised-attention"
        },
        {
          "begin": 1125,
          "end": 1131,
          "code": "424.1",
          "code_system": "ICD-9-CM",
          "type": "ECAN-supervised-attention"
        },
        {
          "begin": 3034,
          "end": 3040,
          "code": "424.1",
          "code_system": "ICD-9-CM",
          "type": "ECAN-supervised-attention"
        },
        {
          "begin": 4196,
          "end": 4220,
          "code": "424.1",
          "code_system": "ICD-9-CM",
          "type": "ECAN-supervised-attention"
        },
        {
          "begin": 7100,
          "end": 7106,
          "code": "424.1",
          "code_system": "ICD-9-CM",
          "type": "ECAN-supervised-attention"
        },
        {
          "begin": 692,
          "end": 703,
          "code": "429.3",
          "code_system": "ICD-9-CM",
          "type": "ECAN-supervised-attention"
        },
        {
          "begin": 7107,
          "end": 7115,
          "code": "440.0",
          "code_system": "ICD-9-CM",
          "type": "ECAN-supervised-attention"
        },
        {
          "begin": 1186,
          "end": 1192,
          "code": "493.90",
          "code_system": "ICD-9-CM",
          "type": "ECAN-supervised-attention"
        },
        {
          "begin": 5396,
          "end": 5402,
          "code": "493.90",
          "code_system": "ICD-9-CM",
          "type": "ECAN-supervised-attention"
        },
        {
          "begin": 7161,
          "end": 7167,
          "code": "493.90",
          "code_system": "ICD-9-CM",
          "type": "ECAN-supervised-attention"
        },
        {
          "begin": 1175,
          "end": 1185,
          "code": "593.2",
          "code_system": "ICD-9-CM",
          "type": "ECAN-supervised-attention"
        },
        {
          "begin": 7150,
          "end": 7160,
          "code": "593.2",
          "code_system": "ICD-9-CM",
          "type": "ECAN-supervised-attention"
        },
        {
          "begin": 692,
          "end": 703,
          "code": "782.3",
          "code_system": "ICD-9-CM",
          "type": "ECAN-supervised-attention"
        },
        {
          "begin": 708,
          "end": 714,
          "code": "782.3",
          "code_system": "ICD-9-CM",
          "type": "ECAN-supervised-attention"
        },
        {
          "begin": 1181,
          "end": 1185,
          "code": "782.3",
          "code_system": "ICD-9-CM",
          "type": "ECAN-supervised-attention"
        },
        {
          "begin": 2067,
          "end": 2072,
          "code": "782.3",
          "code_system": "ICD-9-CM",
          "type": "ECAN-supervised-attention"
        },
        {
          "begin": 6940,
          "end": 6945,
          "code": "782.3",
          "code_system": "ICD-9-CM",
          "type": "ECAN-supervised-attention"
        },
        {
          "begin": 7156,
          "end": 7160,
          "code": "782.3",
          "code_system": "ICD-9-CM",
          "type": "ECAN-supervised-attention"
        },
        {
          "begin": 531,
          "end": 537,
          "code": "785.2",
          "code_system": "ICD-9-CM",
          "type": "ECAN-supervised-attention"
        },
        {
          "begin": 4150,
          "end": 4154,
          "code": "785.2",
          "code_system": "ICD-9-CM",
          "type": "ECAN-supervised-attention"
        },
        {
          "begin": 4610,
          "end": 4619,
          "code": "785.2",
          "code_system": "ICD-9-CM",
          "type": "ECAN-supervised-attention"
        },
        {
          "begin": 7319,
          "end": 7326,
          "code": "785.2",
          "code_system": "ICD-9-CM",
          "type": "ECAN-supervised-attention"
        },
        {
          "begin": 280,
          "end": 288,
          "code": "786.02",
          "code_system": "ICD-9-CM",
          "type": "ECAN-supervised-attention"
        },
        {
          "begin": 782,
          "end": 798,
          "code": "786.02",
          "code_system": "ICD-9-CM",
          "type": "ECAN-supervised-attention"
        },
        {
          "begin": 269,
          "end": 276,
          "code": "786.05",
          "code_system": "ICD-9-CM",
          "type": "ECAN-supervised-attention"
        },
        {
          "begin": 280,
          "end": 288,
          "code": "786.05",
          "code_system": "ICD-9-CM",
          "type": "ECAN-supervised-attention"
        },
        {
          "begin": 756,
          "end": 763,
          "code": "786.05",
          "code_system": "ICD-9-CM",
          "type": "ECAN-supervised-attention"
        },
        {
          "begin": 767,
          "end": 775,
          "code": "786.05",
          "code_system": "ICD-9-CM",
          "type": "ECAN-supervised-attention"
        },
        {
          "begin": 789,
          "end": 798,
          "code": "786.05",
          "code_system": "ICD-9-CM",
          "type": "ECAN-supervised-attention"
        },
        {
          "begin": 7100,
          "end": 7106,
          "code": "786.05",
          "code_system": "ICD-9-CM",
          "type": "ECAN-supervised-attention"
        }
      ]
    },
    {
      "note_id": 1242220,
      "category": "Radiology",
      "description": "CAROTID SERIES COMPLETE",
      "annotations": [
        {
          "begin": 161,
          "end": 168,
          "code": "433.10",
          "code_system": "ICD-9-CM",
          "type": "ECAN-supervised-attention"
        },
        {
          "begin": 663,
          "end": 670,
          "code": "433.10",
          "code_system": "ICD-9-CM",
          "type": "ECAN-supervised-attention"
        },
        {
          "begin": 1490,
          "end": 1493,
          "code": "433.10",
          "code_system": "ICD-9-CM",
          "type": "ECAN-supervised-attention"
        },
        {
          "begin": 24,
          "end": 47,
          "code": "93880",
          "code_system": "CPT",
          "type": "ECAN-supervised-attention"
        },
        {
          "begin": 161,
          "end": 168,
          "code": "93880",
          "code_system": "CPT",
          "type": "ECAN-supervised-attention"
        },
        {
          "begin": 375,
          "end": 382,
          "code": "93880",
          "code_system": "CPT",
          "type": "ECAN-supervised-attention"
        },
        {
          "begin": 535,
          "end": 545,
          "code": "93880",
          "code_system": "CPT",
          "type": "ECAN-supervised-attention"
        },
        {
          "begin": 555,
          "end": 562,
          "code": "93880",
          "code_system": "CPT",
          "type": "ECAN-supervised-attention"
        }
      ]
    },
    {
      "note_id": 1242401,
      "category": "Radiology",
      "description": "CHEST PORT. LINE PLACEMENT",
      "annotations": [
        {
          "begin": 781,
          "end": 783,
          "code": "36556",
          "code_system": "CPT",
          "type": "ECAN-supervised-attention"
        },
        {
          "begin": 1038,
          "end": 1049,
          "code": "518.0",
          "code_system": "ICD-9-CM",
          "type": "ECAN-supervised-attention"
        }
      ]
    },
    {
      "note_id": 1242557,
      "category": "Radiology",
      "description": "CHEST (PORTABLE AP)",
      "annotations": [
        {
          "begin": 24,
          "end": 42,
          "code": "71045",
          "code_system": "CPT",
          "type": "ECAN-supervised-attention"
        },
        {
          "begin": 400,
          "end": 403,
          "code": "786.05",
          "code_system": "ICD-9-CM",
          "type": "ECAN-supervised-attention"
        },
        {
          "begin": 646,
          "end": 655,
          "code": "786.05",
          "code_system": "ICD-9-CM",
          "type": "ECAN-supervised-attention"
        }
      ]
    },
    {
      "note_id": 1242726,
      "category": "Radiology",
      "description": "CHEST (PORTABLE AP)",
      "annotations": [
        {
          "begin": 1622,
          "end": 1634,
          "code": "429.3",
          "code_system": "ICD-9-CM",
          "type": "ECAN-supervised-attention"
        },
        {
          "begin": 24,
          "end": 42,
          "code": "71045",
          "code_system": "CPT",
          "type": "ECAN-supervised-attention"
        },
        {
          "begin": 926,
          "end": 944,
          "code": "793.19",
          "code_system": "ICD-9-CM",
          "type": "ECAN-supervised-attention"
        },
        {
          "begin": 1063,
          "end": 1070,
          "code": "793.19",
          "code_system": "ICD-9-CM",
          "type": "ECAN-supervised-attention"
        },
        {
          "begin": 1517,
          "end": 1524,
          "code": "793.19",
          "code_system": "ICD-9-CM",
          "type": "ECAN-supervised-attention"
        }
      ]
    },
    {
      "note_id": 1242610,
      "category": "Radiology",
      "description": "CHEST (PORTABLE AP)",
      "annotations": [
        {
          "begin": 166,
          "end": 173,
          "code": "511.9",
          "code_system": "ICD-9-CM",
          "type": "ECAN-supervised-attention"
        },
        {
          "begin": 671,
          "end": 678,
          "code": "511.9",
          "code_system": "ICD-9-CM",
          "type": "ECAN-supervised-attention"
        },
        {
          "begin": 925,
          "end": 932,
          "code": "511.9",
          "code_system": "ICD-9-CM",
          "type": "ECAN-supervised-attention"
        },
        {
          "begin": 812,
          "end": 823,
          "code": "518.0",
          "code_system": "ICD-9-CM",
          "type": "ECAN-supervised-attention"
        },
        {
          "begin": 955,
          "end": 966,
          "code": "518.0",
          "code_system": "ICD-9-CM",
          "type": "ECAN-supervised-attention"
        },
        {
          "begin": 25,
          "end": 40,
          "code": "71045",
          "code_system": "CPT",
          "type": "ECAN-supervised-attention"
        },
        {
          "begin": 406,
          "end": 409,
          "code": "786.05",
          "code_system": "ICD-9-CM",
          "type": "ECAN-supervised-attention"
        },
        {
          "begin": 807,
          "end": 811,
          "code": "793.19",
          "code_system": "ICD-9-CM",
          "type": "ECAN-supervised-attention"
        },
        {
          "begin": 853,
          "end": 871,
          "code": "793.19",
          "code_system": "ICD-9-CM",
          "type": "ECAN-supervised-attention"
        }
      ]
    },
    {
      "note_id": 1243050,
      "category": "Radiology",
      "description": "CHEST (PA & LAT)",
      "annotations": [
        {
          "begin": 1088,
          "end": 1099,
          "code": "518.0",
          "code_system": "ICD-9-CM",
          "type": "ECAN-supervised-attention"
        },
        {
          "begin": 26,
          "end": 41,
          "code": "71046",
          "code_system": "CPT",
          "type": "ECAN-supervised-attention"
        }
      ]
    },
    {
      "note_id": 1242797,
      "category": "Radiology",
      "description": "CHEST (PORTABLE AP)",
      "annotations": [
        {
          "begin": 25,
          "end": 43,
          "code": "71045",
          "code_system": "CPT",
          "type": "ECAN-supervised-attention"
        }
      ]
    },
    {
      "note_id": 1242314,
      "category": "Radiology",
      "description": "CHEST (PRE-OP PA & LAT)",
      "annotations": [
        {
          "begin": 25,
          "end": 47,
          "code": "71046",
          "code_system": "CPT",
          "type": "ECAN-supervised-attention"
        },
        {
          "begin": 271,
          "end": 274,
          "code": "V42.2",
          "code_system": "ICD-9-CM",
          "type": "ECAN-supervised-attention"
        }
      ]
    }
  ]
}