{"hadm_id": 148583, "comment": "", "notes": [{"note_id": 47227, "category": "Discharge summary", "description": "Report", "annotations": [{"begin": 427, "end": 438, "code": "Z92.82", "code_system": "ICD-10-CM", "description": "Status post administration of tPA (rtPA) in a different facility within the last 24 hours prior to admission to current facility", "type": "Human"}, {"begin": 1346, "end": 1349, "code": "I10", "code_system": "ICD-10-CM", "description": "Essential (primary) hypertension", "type": "Human"}, {"begin": 1351, "end": 1355, "code": "K21.9", "code_system": "ICD-10-CM", "description": "Gastro-esophageal reflux disease without esophagitis", "type": "Human"}, {"begin": 1435, "end": 1441, "code": "F17.200", "code_system": "ICD-10-CM", "description": "Nicotine dependence, unspecified, uncomplicated", "type": "Human"}, {"begin": 5759, "end": 5769, "code": "H53.47", "code_system": "ICD-10-CM", "description": "Heteronymous bilateral field defects", "type": "Human"}, {"begin": 7550, "end": 7570, "code": "G43.109", "code_system": "ICD-10-CM", "description": "Migraine with aura, not intractable, without status migrainosus", "type": "Human"}]}]}
