{"hadm_id": 182386, "comment": "Amputatation- Need OP note to Validate PCS", "notes": [{"note_id": 647746, "category": "Physician", "description": "Intensivist Note", "annotations": [{"begin": 74, "end": 116, "code": "S68.611A", "code_system": "ICD-10-CM", "description": "Complete traumatic transphalangeal amputation of left index finger, initial encounter", "type": "Human"}, {"begin": 121, "end": 124, "code": "S68.613A", "code_system": "ICD-10-CM", "description": "Complete traumatic transphalangeal amputation of left middle finger, initial encounter", "type": "Human"}, {"begin": 5532, "end": 5543, "code": "S62.605A", "code_system": "ICD-10-CM", "description": "Fracture of unspecified phalanx of left ring finger, initial encounter for closed fracture", "type": "Human"}, {"begin": 5564, "end": 5581, "code": "S62.603A", "code_system": "ICD-10-CM", "description": "Fracture of unspecified phalanx of left middle finger, initial encounter for closed fracture", "type": "Human"}, {"begin": 5625, "end": 5643, "code": "S62.607A", "code_system": "ICD-10-CM", "description": "Fracture of unspecified phalanx of left little finger, initial encounter for closed fracture", "type": "Human"}]}, {"note_id": 648151, "category": "Physician", "description": "Intensivist Note", "annotations": [{"begin": 48, "end": 69, "code": "W31.2XXA", "code_system": "ICD-10-CM", "description": "Contact with powered woodworking and forming machines, initial encounter", "type": "Human"}]}, {"note_id": 5539, "category": "Discharge summary", "description": "Report", "annotations": [{"begin": 1059, "end": 1072, "code": "F17.200", "code_system": "ICD-10-CM", "description": "Nicotine dependence, unspecified, uncomplicated", "type": "Human"}]}, {"note_id": 647308, "category": "Physician", "description": "Intensivist Note", "annotations": [{"begin": 708, "end": 717, "code": "L40.9", "code_system": "ICD-10-CM", "description": "Psoriasis, unspecified", "type": "Human"}]}]}
