{"hadm_id": 122180, "comment": "OP notes missing-unable to validate PCS codes", "notes": [{"note_id": 461668, "category": "Physician", "description": "Intensivist Note", "annotations": [{"begin": 5578, "end": 5591, "code": "790.29", "code_system": "ICD-9-CM", "description": "Other abnormal glucose", "type": "MapType.APPROX"}]}, {"note_id": 458212, "category": "Physician", "description": "Intensivist Note", "annotations": [{"begin": 7426, "end": 7429, "code": "V49.86", "code_system": "ICD-9-CM", "description": "Do not resuscitate status", "type": "MapType.EXACT"}]}, {"note_id": 462146, "category": "Physician", "description": "Intensivist Note", "annotations": [{"begin": 3017, "end": 3022, "code": "278.00", "code_system": "ICD-9-CM", "description": "Obesity, unspecified", "type": "MapType.APPROX"}]}, {"note_id": 459734, "category": "Physician", "description": "Intensivist Note", "annotations": [{"begin": 7577, "end": 7603, "code": "96.72", "code_system": "ICD-9-PCS", "description": "Continuous mechanical ventilation for 96 consecutive hours or more", "type": "Human"}]}, {"note_id": 457739, "category": "Physician", "description": "Intensivist Note", "annotations": [{"begin": 5211, "end": 5237, "code": "518.81", "code_system": "ICD-9-CM", "description": "Acute respiratory failure", "type": "Human"}]}, {"note_id": 460910, "category": "Physician", "description": "Intensivist Note", "annotations": [{"begin": 8146, "end": 8150, "code": "93.90", "code_system": "ICD-9-PCS", "description": "Continuous positive airway pressure [CPAP]", "type": "MapType.APPROX"}]}, {"note_id": 457266, "category": "Nutrition", "description": "Clinical Nutrition Note", "annotations": [{"begin": 409, "end": 412, "code": "414.01", "code_system": "ICD-9-CM", "description": "Coronary atherosclerosis of native coronary artery", "type": "MapType.MULTI_DESC"}, {"begin": 2560, "end": 2570, "code": "96.6", "code_system": "ICD-9-PCS", "description": "Enteral infusion of concentrated nutritional substances", "type": "Human"}]}, {"note_id": 36379, "category": "Discharge summary", "description": "Report", "annotations": [{"begin": 934, "end": 938, "code": "V45.81", "code_system": "ICD-9-CM", "description": "Postsurgical aortocoronary bypass status", "type": "Human"}, {"begin": 957, "end": 960, "code": "401.9", "code_system": "ICD-9-CM", "description": "Unspecified essential hypertension", "type": "Human"}, {"begin": 10986, "end": 10997, "code": "458.9", "code_system": "ICD-9-CM", "description": "Hypotension, unspecified", "type": "MapType.EXACT"}, {"begin": 11048, "end": 11051, "code": "430", "code_system": "ICD-9-CM", "description": "Subarachnoid hemorrhage", "type": "Human"}, {"begin": 11057, "end": 11060, "code": "431", "code_system": "ICD-9-CM", "description": "Intracerebral hemorrhage", "type": "MapType.APPROX"}, {"begin": 11546, "end": 11566, "code": "437.3", "code_system": "ICD-9-CM", "description": "Cerebral aneurysm, nonruptured", "type": "MapType.APPROX"}, {"begin": 12354, "end": 12376, "code": "434.91", "code_system": "ICD-9-CM", "description": "Cerebral artery occlusion, unspecified, with cerebral infarction", "type": "Human"}, {"begin": 15433, "end": 15460, "code": "431", "code_system": "ICD-9-CM", "description": "Intracerebral hemorrhage", "type": "MapType.APPROX"}, {"begin": 15462, "end": 15485, "code": "430", "code_system": "ICD-9-CM", "description": "Subarachnoid hemorrhage", "type": "Human"}, {"begin": 15487, "end": 15504, "code": "437.3", "code_system": "ICD-9-CM", "description": "Cerebral aneurysm, nonruptured", "type": "MapType.APPROX"}, {"begin": 15514, "end": 15520, "code": "410.71", "code_system": "ICD-9-CM", "description": "Acute myocardial infarction, subendocardial infarction, initial episode of care", "type": "Human"}]}]}
