{"hadm_id": 150755, "comment": "", "notes": [{"note_id": 35953, "category": "Discharge summary", "description": "Report", "annotations": [{"begin": 437, "end": 441, "code": "493.22", "code_system": "ICD-9-CM", "description": "Chronic obstructive asthma, with acute exacerbation", "type": "Human"}, {"begin": 4239, "end": 4262, "code": "414.01", "code_system": "ICD-9-CM", "description": "Coronary atherosclerosis of native coronary artery", "type": "Human"}, {"begin": 8364, "end": 8389, "code": "428.23", "code_system": "ICD-9-CM", "description": "Systolic heart failure, acute on chronic", "type": "Human"}, {"begin": 12394, "end": 12413, "code": "427.31", "code_system": "ICD-9-CM", "description": "Atrial fibrillation", "type": "Human"}]}, {"note_id": 651746, "category": "Physician", "description": "Physician Resident Admission Note", "annotations": [{"begin": 8846, "end": 8857, "code": "995.27", "code_system": "ICD-9-CM", "description": "Other drug allergy", "type": "Human"}]}]}
