{
  "hadm_id": 158734,
  "notes": [
    {
      "note_id": 48799,
      "category": "Discharge summary",
      "description": "Report",
      "annotations": [
        {
          "begin": 1125,
          "end": 1136,
          "code": "135",
          "code_system": "ICD-9-CM",
          "type": "ECAN-unsupervised-attention"
        },
        {
          "begin": 1176,
          "end": 1184,
          "code": "250.00",
          "code_system": "ICD-9-CM",
          "type": "ECAN-unsupervised-attention"
        },
        {
          "begin": 5878,
          "end": 5882,
          "code": "250.00",
          "code_system": "ICD-9-CM",
          "type": "ECAN-unsupervised-attention"
        },
        {
          "begin": 1246,
          "end": 1258,
          "code": "272.4",
          "code_system": "ICD-9-CM",
          "type": "ECAN-unsupervised-attention"
        },
        {
          "begin": 5878,
          "end": 5882,
          "code": "272.4",
          "code_system": "ICD-9-CM",
          "type": "ECAN-unsupervised-attention"
        },
        {
          "begin": 1189,
          "end": 1196,
          "code": "278.00",
          "code_system": "ICD-9-CM",
          "type": "ECAN-unsupervised-attention"
        },
        {
          "begin": 9260,
          "end": 9263,
          "code": "327.23",
          "code_system": "ICD-9-CM",
          "type": "ECAN-unsupervised-attention"
        },
        {
          "begin": 1263,
          "end": 1271,
          "code": "355.1",
          "code_system": "ICD-9-CM",
          "type": "ECAN-unsupervised-attention"
        },
        {
          "begin": 1201,
          "end": 1213,
          "code": "401.9",
          "code_system": "ICD-9-CM",
          "type": "ECAN-unsupervised-attention"
        },
        {
          "begin": 9264,
          "end": 9276,
          "code": "401.9",
          "code_system": "ICD-9-CM",
          "type": "ECAN-unsupervised-attention"
        },
        {
          "begin": 459,
          "end": 468,
          "code": "571.5",
          "code_system": "ICD-9-CM",
          "type": "ECAN-unsupervised-attention"
        },
        {
          "begin": 914,
          "end": 923,
          "code": "571.5",
          "code_system": "ICD-9-CM",
          "type": "ECAN-unsupervised-attention"
        },
        {
          "begin": 5771,
          "end": 5774,
          "code": "571.5",
          "code_system": "ICD-9-CM",
          "type": "ECAN-unsupervised-attention"
        },
        {
          "begin": 9237,
          "end": 9244,
          "code": "572.2",
          "code_system": "ICD-9-CM",
          "type": "ECAN-unsupervised-attention"
        },
        {
          "begin": 5961,
          "end": 5966,
          "code": "814.00",
          "code_system": "ICD-9-CM",
          "type": "ECAN-unsupervised-attention"
        },
        {
          "begin": 5944,
          "end": 5947,
          "code": "824.8",
          "code_system": "ICD-9-CM",
          "type": "ECAN-unsupervised-attention"
        },
        {
          "begin": 757,
          "end": 765,
          "code": "852.21",
          "code_system": "ICD-9-CM",
          "type": "ECAN-unsupervised-attention"
        },
        {
          "begin": 9210,
          "end": 9218,
          "code": "852.21",
          "code_system": "ICD-9-CM",
          "type": "ECAN-unsupervised-attention"
        },
        {
          "begin": 509,
          "end": 512,
          "code": "V12.51",
          "code_system": "ICD-9-CM",
          "type": "ECAN-unsupervised-attention"
        },
        {
          "begin": 1344,
          "end": 1347,
          "code": "V12.51",
          "code_system": "ICD-9-CM",
          "type": "ECAN-unsupervised-attention"
        },
        {
          "begin": 5839,
          "end": 5842,
          "code": "V12.51",
          "code_system": "ICD-9-CM",
          "type": "ECAN-unsupervised-attention"
        },
        {
          "begin": 5872,
          "end": 5876,
          "code": "V12.51",
          "code_system": "ICD-9-CM",
          "type": "ECAN-unsupervised-attention"
        },
        {
          "begin": 6808,
          "end": 6812,
          "code": "V12.51",
          "code_system": "ICD-9-CM",
          "type": "ECAN-unsupervised-attention"
        },
        {
          "begin": 1560,
          "end": 1564,
          "code": "V15.82",
          "code_system": "ICD-9-CM",
          "type": "ECAN-unsupervised-attention"
        },
        {
          "begin": 1581,
          "end": 1588,
          "code": "V15.82",
          "code_system": "ICD-9-CM",
          "type": "ECAN-unsupervised-attention"
        },
        {
          "begin": 1593,
          "end": 1597,
          "code": "V15.82",
          "code_system": "ICD-9-CM",
          "type": "ECAN-unsupervised-attention"
        },
        {
          "begin": 1652,
          "end": 1658,
          "code": "V15.82",
          "code_system": "ICD-9-CM",
          "type": "ECAN-unsupervised-attention"
        },
        {
          "begin": 509,
          "end": 512,
          "code": "V54.12",
          "code_system": "ICD-9-CM",
          "type": "ECAN-unsupervised-attention"
        },
        {
          "begin": 516,
          "end": 523,
          "code": "V54.12",
          "code_system": "ICD-9-CM",
          "type": "ECAN-unsupervised-attention"
        },
        {
          "begin": 5856,
          "end": 5863,
          "code": "V54.12",
          "code_system": "ICD-9-CM",
          "type": "ECAN-unsupervised-attention"
        }
      ]
    }
  ]
}