{"hadm_id": 128511, "comment": "", "notes": [{"note_id": 652235, "category": "Physician", "description": "Physician Resident Admission Note", "annotations": [{"begin": 18, "end": 23, "code": "780.60", "code_system": "ICD-9-CM", "description": "NO_DEF", "type": "MapType.APPROX"}, {"begin": 25, "end": 33, "code": "789.01", "code_system": "ICD-9-CM", "description": "Abdominal pain, right upper quadrant", "type": "MapType.EXACT"}, {"begin": 96, "end": 99, "code": "428.0", "code_system": "ICD-9-CM", "description": "Congestive heart failure, unspecified", "type": "MapType.MULTI"}, {"begin": 101, "end": 115, "code": "569.5", "code_system": "ICD-9-CM", "description": "Abscess of intestine", "type": "MapType.MULTI_DESC"}, {"begin": 248, "end": 256, "code": "787.91", "code_system": "ICD-9-CM", "description": "Diarrhea", "type": "MapType.APPROX"}, {"begin": 258, "end": 261, "code": "787.3", "code_system": "ICD-9-CM", "description": "Flatulence, eructation, and gas pain", "type": "MapType.APPROX"}, {"begin": 269, "end": 282, "code": "789.01", "code_system": "ICD-9-CM", "description": "Abdominal pain, right upper quadrant", "type": "MapType.EXACT"}, {"begin": 337, "end": 345, "code": "787.91", "code_system": "ICD-9-CM", "description": "Diarrhea", "type": "MapType.APPROX"}, {"begin": 418, "end": 426, "code": "787.91", "code_system": "ICD-9-CM", "description": "Diarrhea", "type": "MapType.APPROX"}, {"begin": 544, "end": 552, "code": "787.91", "code_system": "ICD-9-CM", "description": "Diarrhea", "type": "MapType.APPROX"}, {"begin": 671, "end": 680, "code": "780.79", "code_system": "ICD-9-CM", "description": "Other malaise and fatigue", "type": "MapType.APPROX"}, {"begin": 879, "end": 884, "code": "780.60", "code_system": "ICD-9-CM", "description": "NO_DEF", "type": "MapType.APPROX"}, {"begin": 915, "end": 923, "code": "787.03", "code_system": "ICD-9-CM", "description": "Vomiting alone", "type": "MapType.MULTI_DESC"}, {"begin": 1063, "end": 1070, "code": "780.60", "code_system": "ICD-9-CM", "description": "NO_DEF", "type": "MapType.APPROX"}, {"begin": 1100, "end": 1118, "code": "574.20", "code_system": "ICD-9-CM", "description": "Calculus of gallbladder without mention of cholecystitis, without mention of obstruction", "type": "MapType.APPROX"}, {"begin": 1313, "end": 1324, "code": "785.0", "code_system": "ICD-9-CM", "description": "Tachycardia, unspecified", "type": "MapType.EXACT"}, {"begin": 1353, "end": 1385, "code": "792.1", "code_system": "ICD-9-CM", "description": "Nonspecific abnormal findings in stool contents", "type": "MapType.MULTI_DESC"}, {"begin": 1489, "end": 1501, "code": "528.5", "code_system": "ICD-9-CM", "description": "Diseases of lips", "type": "MapType.EXACT"}, {"begin": 1754, "end": 1762, "code": "787.91", "code_system": "ICD-9-CM", "description": "Diarrhea", "type": "MapType.APPROX"}, {"begin": 1911, "end": 1925, "code": "543.9", "code_system": "ICD-9-CM", "description": "Other and unspecified diseases of appendix", "type": "MapType.APPROX"}, {"begin": 1990, "end": 2004, "code": "244.9", "code_system": "ICD-9-CM", "description": "Unspecified hypothyroidism", "type": "Human"}, {"begin": 2008, "end": 2014, "code": "553.9", "code_system": "ICD-9-CM", "description": "Hernia of unspecified site without mention of obstruction or gangrene", "type": "MapType.MULTI_DESC"}, {"begin": 2166, "end": 2180, "code": "789.01", "code_system": "ICD-9-CM", "description": "Abdominal pain, right upper quadrant", "type": "MapType.EXACT"}, {"begin": 2182, "end": 2188, "code": "787.02", "code_system": "ICD-9-CM", "description": "Nausea alone", "type": "MapType.EXACT"}, {"begin": 2190, "end": 2198, "code": "787.91", "code_system": "ICD-9-CM", "description": "Diarrhea", "type": "MapType.APPROX"}, {"begin": 4701, "end": 4720, "code": "574.20", "code_system": "ICD-9-CM", "description": "Calculus of gallbladder without mention of cholecystitis, without mention of obstruction", "type": "MapType.APPROX"}]}, {"note_id": 652294, "category": "Physician", "description": "Physician Attending Admission Note - MICU", "annotations": [{"begin": 18, "end": 24, "code": "995.91", "code_system": "ICD-9-CM", "description": "Sepsis", "type": "MapType.MULTI_DESC"}, {"begin": 303, "end": 311, "code": "787.91", "code_system": "ICD-9-CM", "description": "Diarrhea", "type": "MapType.APPROX"}, {"begin": 404, "end": 412, "code": "787.91", "code_system": "ICD-9-CM", "description": "Diarrhea", "type": "MapType.APPROX"}, {"begin": 999, "end": 1007, "code": "787.91", "code_system": "ICD-9-CM", "description": "Diarrhea", "type": "MapType.APPROX"}, {"begin": 1208, "end": 1220, "code": "528.5", "code_system": "ICD-9-CM", "description": "Diseases of lips", "type": "MapType.EXACT"}, {"begin": 1408, "end": 1411, "code": "428.0", "code_system": "ICD-9-CM", "description": "Congestive heart failure, unspecified", "type": "MapType.MULTI"}, {"begin": 5928, "end": 5947, "code": "574.00", "code_system": "ICD-9-CM", "description": "Calculus of gallbladder with acute cholecystitis, without mention of obstruction", "type": "MapType.APPROX"}, {"begin": 5949, "end": 5957, "code": "787.91", "code_system": "ICD-9-CM", "description": "Diarrhea", "type": "MapType.APPROX"}]}, {"note_id": 240397, "category": "ECG", "description": "Report", "annotations": [{"begin": 0, "end": 12, "code": "93000", "code_system": "CPT", "description": "Electrocardiogram, routine ECG with at least 12 leads; with interpretation and report", "type": "Human"}, {"begin": 25, "end": 59, "code": "794.31", "code_system": "ICD-9-CM", "description": "Nonspecific abnormal electrocardiogram [ECG] [EKG]", "type": "MapType.EXACT"}]}, {"note_id": 652377, "category": "Physician", "description": "Physician Attending Admission Note - MICU", "annotations": [{"begin": 18, "end": 38, "code": "770.89", "code_system": "ICD-9-CM", "description": "Other respiratory problems after birth", "type": "MapType.MULTI_DESC"}, {"begin": 331, "end": 342, "code": "041.6", "code_system": "ICD-9-CM", "description": "Proteus (mirabilis) (morganii) infection in conditions classified elsewhere and of unspecified site", "type": "MapType.EXACT"}, {"begin": 350, "end": 371, "code": "780.97", "code_system": "ICD-9-CM", "description": "Altered mental status", "type": "MapType.APPROX"}, {"begin": 468, "end": 478, "code": "518.4", "code_system": "ICD-9-CM", "description": "Acute edema of lung, unspecified", "type": "MapType.EXACT"}, {"begin": 1126, "end": 1138, "code": "528.5", "code_system": "ICD-9-CM", "description": "Diseases of lips", "type": "MapType.EXACT"}, {"begin": 1524, "end": 1527, "code": "401.9", "code_system": "ICD-9-CM", "description": "Unspecified essential hypertension", "type": "MapType.MULTI_DESC"}, {"begin": 1531, "end": 1540, "code": "716.20", "code_system": "ICD-9-CM", "description": "Allergic arthritis, site unspecified", "type": "MapType.APPROX"}, {"begin": 1544, "end": 1550, "code": "285.9", "code_system": "ICD-9-CM", "description": "Anemia, unspecified", "type": "Human"}, {"begin": 1554, "end": 1566, "code": "273.3", "code_system": "ICD-9-CM", "description": "Macroglobulinemia", "type": "MapType.APPROX"}, {"begin": 1804, "end": 1811, "code": "780.79", "code_system": "ICD-9-CM", "description": "Other malaise and fatigue", "type": "MapType.APPROX"}, {"begin": 1813, "end": 1818, "code": "780.60", "code_system": "ICD-9-CM", "description": "NO_DEF", "type": "MapType.APPROX"}, {"begin": 1870, "end": 1880, "code": "786.50", "code_system": "ICD-9-CM", "description": "Unspecified chest pain", "type": "MapType.EXACT"}, {"begin": 1882, "end": 1893, "code": "786.06", "code_system": "ICD-9-CM", "description": "Tachypnea", "type": "MapType.EXACT"}, {"begin": 1895, "end": 1904, "code": "786.02", "code_system": "ICD-9-CM", "description": "Orthopnea", "type": "MapType.EXACT"}, {"begin": 1921, "end": 1928, "code": "786.09", "code_system": "ICD-9-CM", "description": "Other dyspnea and respiratory abnormality", "type": "MapType.APPROX"}, {"begin": 1941, "end": 1947, "code": "786.07", "code_system": "ICD-9-CM", "description": "Wheezing", "type": "MapType.EXACT"}, {"begin": 2021, "end": 2027, "code": "285.9", "code_system": "ICD-9-CM", "description": "Anemia, unspecified", "type": "Human"}, {"begin": 3908, "end": 3929, "code": "786.09", "code_system": "ICD-9-CM", "description": "Other dyspnea and respiratory abnormality", "type": "MapType.MULTI_DESC"}, {"begin": 4884, "end": 4898, "code": "574.00", "code_system": "ICD-9-CM", "description": "Calculus of gallbladder with acute cholecystitis, without mention of obstruction", "type": "MapType.APPROX"}]}, {"note_id": 652516, "category": "Physician", "description": "Physician Resident Progress Note", "annotations": [{"begin": 520, "end": 532, "code": "528.5", "code_system": "ICD-9-CM", "description": "Diseases of lips", "type": "MapType.EXACT"}, {"begin": 2872, "end": 2875, "code": "789.04", "code_system": "ICD-9-CM", "description": "Abdominal pain, left lower quadrant", "type": "MapType.EXACT"}, {"begin": 2877, "end": 2880, "code": "789.03", "code_system": "ICD-9-CM", "description": "Abdominal pain, right lower quadrant", "type": "MapType.EXACT"}, {"begin": 3819, "end": 3822, "code": "428.0", "code_system": "ICD-9-CM", "description": "Congestive heart failure, unspecified", "type": "MapType.MULTI"}, {"begin": 3831, "end": 3839, "code": "787.91", "code_system": "ICD-9-CM", "description": "Diarrhea", "type": "MapType.APPROX"}, {"begin": 3847, "end": 3866, "code": "574.20", "code_system": "ICD-9-CM", "description": "Calculus of gallbladder without mention of cholecystitis, without mention of obstruction", "type": "MapType.APPROX"}, {"begin": 3978, "end": 3986, "code": "787.91", "code_system": "ICD-9-CM", "description": "Diarrhea", "type": "MapType.APPROX"}, {"begin": 4087, "end": 4092, "code": "780.60", "code_system": "ICD-9-CM", "description": "NO_DEF", "type": "MapType.APPROX"}, {"begin": 4108, "end": 4116, "code": "789.01", "code_system": "ICD-9-CM", "description": "Abdominal pain, right upper quadrant", "type": "MapType.EXACT"}, {"begin": 4121, "end": 4140, "code": "574.20", "code_system": "ICD-9-CM", "description": "Calculus of gallbladder without mention of cholecystitis, without mention of obstruction", "type": "MapType.APPROX"}, {"begin": 4275, "end": 4283, "code": "789.01", "code_system": "ICD-9-CM", "description": "Abdominal pain, right upper quadrant", "type": "MapType.EXACT"}, {"begin": 4324, "end": 4327, "code": "789.04", "code_system": "ICD-9-CM", "description": "Abdominal pain, left lower quadrant", "type": "MapType.EXACT"}, {"begin": 4588, "end": 4596, "code": "787.91", "code_system": "ICD-9-CM", "description": "Diarrhea", "type": "MapType.APPROX"}, {"begin": 4670, "end": 4678, "code": "787.91", "code_system": "ICD-9-CM", "description": "Diarrhea", "type": "MapType.APPROX"}, {"begin": 4683, "end": 4697, "code": "569.5", "code_system": "ICD-9-CM", "description": "Abscess of intestine", "type": "MapType.MULTI_DESC"}, {"begin": 4734, "end": 4742, "code": "787.91", "code_system": "ICD-9-CM", "description": "Diarrhea", "type": "MapType.APPROX"}, {"begin": 4827, "end": 4839, "code": "790.6", "code_system": "ICD-9-CM", "description": "Other abnormal blood chemistry", "type": "MapType.MULTI_DESC"}, {"begin": 4970, "end": 4978, "code": "787.91", "code_system": "ICD-9-CM", "description": "Diarrhea", "type": "MapType.APPROX"}]}, {"note_id": 652503, "category": "Physician", "description": "MICU staff progress note", "annotations": [{"begin": 314, "end": 317, "code": "428.0", "code_system": "ICD-9-CM", "description": "Congestive heart failure, unspecified", "type": "MapType.MULTI"}, {"begin": 325, "end": 339, "code": "569.5", "code_system": "ICD-9-CM", "description": "Abscess of intestine", "type": "MapType.MULTI_DESC"}, {"begin": 362, "end": 367, "code": "780.60", "code_system": "ICD-9-CM", "description": "NO_DEF", "type": "MapType.APPROX"}, {"begin": 369, "end": 377, "code": "789.01", "code_system": "ICD-9-CM", "description": "Abdominal pain, right upper quadrant", "type": "MapType.EXACT"}, {"begin": 382, "end": 400, "code": "574.20", "code_system": "ICD-9-CM", "description": "Calculus of gallbladder without mention of cholecystitis, without mention of obstruction", "type": "MapType.APPROX"}, {"begin": 427, "end": 435, "code": "787.91", "code_system": "ICD-9-CM", "description": "Diarrhea", "type": "MapType.APPROX"}, {"begin": 684, "end": 692, "code": "787.91", "code_system": "ICD-9-CM", "description": "Diarrhea", "type": "MapType.APPROX"}, {"begin": 862, "end": 865, "code": "789.04", "code_system": "ICD-9-CM", "description": "Abdominal pain, left lower quadrant", "type": "MapType.EXACT"}, {"begin": 1157, "end": 1162, "code": "780.60", "code_system": "ICD-9-CM", "description": "NO_DEF", "type": "MapType.APPROX"}, {"begin": 1178, "end": 1186, "code": "789.01", "code_system": "ICD-9-CM", "description": "Abdominal pain, right upper quadrant", "type": "MapType.EXACT"}, {"begin": 1241, "end": 1249, "code": "787.91", "code_system": "ICD-9-CM", "description": "Diarrhea", "type": "MapType.APPROX"}, {"begin": 1413, "end": 1421, "code": "787.91", "code_system": "ICD-9-CM", "description": "Diarrhea", "type": "MapType.APPROX"}, {"begin": 1425, "end": 1439, "code": "569.5", "code_system": "ICD-9-CM", "description": "Abscess of intestine", "type": "MapType.MULTI_DESC"}, {"begin": 2306, "end": 2314, "code": "787.91", "code_system": "ICD-9-CM", "description": "Diarrhea", "type": "MapType.APPROX"}]}, {"note_id": 35990, "category": "Discharge summary", "description": "Report", "annotations": [{"begin": 209, "end": 215, "code": "995.91", "code_system": "ICD-9-CM", "description": "Sepsis", "type": "MapType.MULTI_DESC"}, {"begin": 341, "end": 344, "code": "428.0", "code_system": "ICD-9-CM", "description": "Congestive heart failure, unspecified", "type": "MapType.MULTI"}, {"begin": 346, "end": 360, "code": "569.5", "code_system": "ICD-9-CM", "description": "Abscess of intestine", "type": "MapType.MULTI_DESC"}, {"begin": 487, "end": 495, "code": "787.91", "code_system": "ICD-9-CM", "description": "Diarrhea", "type": "MapType.APPROX"}, {"begin": 497, "end": 500, "code": "787.3", "code_system": "ICD-9-CM", "description": "Flatulence, eructation, and gas pain", "type": "MapType.APPROX"}, {"begin": 505, "end": 518, "code": "789.01", "code_system": "ICD-9-CM", "description": "Abdominal pain, right upper quadrant", "type": "MapType.EXACT"}, {"begin": 570, "end": 578, "code": "787.91", "code_system": "ICD-9-CM", "description": "Diarrhea", "type": "MapType.APPROX"}, {"begin": 771, "end": 779, "code": "787.91", "code_system": "ICD-9-CM", "description": "Diarrhea", "type": "MapType.APPROX"}, {"begin": 892, "end": 901, "code": "780.79", "code_system": "ICD-9-CM", "description": "Other malaise and fatigue", "type": "MapType.APPROX"}, {"begin": 1124, "end": 1132, "code": "787.03", "code_system": "ICD-9-CM", "description": "Vomiting alone", "type": "MapType.MULTI_DESC"}, {"begin": 1263, "end": 1270, "code": "780.60", "code_system": "ICD-9-CM", "description": "NO_DEF", "type": "MapType.APPROX"}, {"begin": 1297, "end": 1315, "code": "574.20", "code_system": "ICD-9-CM", "description": "Calculus of gallbladder without mention of cholecystitis, without mention of obstruction", "type": "MapType.APPROX"}, {"begin": 1504, "end": 1515, "code": "785.0", "code_system": "ICD-9-CM", "description": "Tachycardia, unspecified", "type": "MapType.EXACT"}, {"begin": 1541, "end": 1573, "code": "792.1", "code_system": "ICD-9-CM", "description": "Nonspecific abnormal findings in stool contents", "type": "MapType.MULTI_DESC"}, {"begin": 1646, "end": 1660, "code": "543.9", "code_system": "ICD-9-CM", "description": "Other and unspecified diseases of appendix", "type": "MapType.APPROX"}, {"begin": 1719, "end": 1733, "code": "244.9", "code_system": "ICD-9-CM", "description": "Unspecified hypothyroidism", "type": "Human"}, {"begin": 1734, "end": 1740, "code": "553.9", "code_system": "ICD-9-CM", "description": "Hernia of unspecified site without mention of obstruction or gangrene", "type": "MapType.MULTI_DESC"}, {"begin": 4636, "end": 4650, "code": "46080", "code_system": "CPT", "description": "Sphincterotomy, anal, division of sphincter (separate procedure)", "type": "Human"}, {"begin": 5417, "end": 5425, "code": "787.91", "code_system": "ICD-9-CM", "description": "Diarrhea", "type": "MapType.APPROX"}, {"begin": 5427, "end": 5433, "code": "780.60", "code_system": "ICD-9-CM", "description": "NO_DEF", "type": "MapType.APPROX"}, {"begin": 5761, "end": 5778, "code": "511.1", "code_system": "ICD-9-CM", "description": "Pleurisy with effusion, with mention of a bacterial cause other than tuberculosis", "type": "MapType.MULTI_DESC"}, {"begin": 5795, "end": 5806, "code": "518.0", "code_system": "ICD-9-CM", "description": "Pulmonary collapse", "type": "MapType.APPROX"}, {"begin": 6773, "end": 6784, "code": "562.11", "code_system": "ICD-9-CM", "description": "Diverticulitis of colon without mention of hemorrhage", "type": "MapType.APPROX"}, {"begin": 7605, "end": 7636, "code": "722.52", "code_system": "ICD-9-CM", "description": "Degeneration of lumbar or lumbosacral intervertebral disc", "type": "MapType.APPROX"}, {"begin": 7873, "end": 7884, "code": "562.11", "code_system": "ICD-9-CM", "description": "Diverticulitis of colon without mention of hemorrhage", "type": "MapType.APPROX"}, {"begin": 7945, "end": 7959, "code": "569.5", "code_system": "ICD-9-CM", "description": "Abscess of intestine", "type": "MapType.MULTI_DESC"}, {"begin": 8165, "end": 8176, "code": "576.8", "code_system": "ICD-9-CM", "description": "Other specified disorders of biliary tract", "type": "MapType.APPROX"}, {"begin": 8216, "end": 8247, "code": "576.9", "code_system": "ICD-9-CM", "description": "Unspecified disorder of biliary tract", "type": "MapType.EXACT"}, {"begin": 8257, "end": 8285, "code": "577.8", "code_system": "ICD-9-CM", "description": "Other specified diseases of pancreas", "type": "MapType.APPROX"}, {"begin": 8366, "end": 8380, "code": "997.41", "code_system": "ICD-9-CM", "description": "NO_DEF", "type": "MapType.EXACT"}, {"begin": 9839, "end": 9842, "code": "428.0", "code_system": "ICD-9-CM", "description": "Congestive heart failure, unspecified", "type": "MapType.MULTI"}, {"begin": 9844, "end": 9858, "code": "569.5", "code_system": "ICD-9-CM", "description": "Abscess of intestine", "type": "MapType.MULTI_DESC"}, {"begin": 9953, "end": 9960, "code": "780.60", "code_system": "ICD-9-CM", "description": "NO_DEF", "type": "MapType.APPROX"}, {"begin": 10342, "end": 10350, "code": "787.91", "code_system": "ICD-9-CM", "description": "Diarrhea", "type": "MapType.APPROX"}, {"begin": 10457, "end": 10469, "code": "288.60", "code_system": "ICD-9-CM", "description": "Leukocytosis, unspecified", "type": "MapType.EXACT"}, {"begin": 10478, "end": 10492, "code": "543.9", "code_system": "ICD-9-CM", "description": "Other and unspecified diseases of appendix", "type": "MapType.APPROX"}, {"begin": 11436, "end": 11450, "code": "569.5", "code_system": "ICD-9-CM", "description": "Abscess of intestine", "type": "MapType.MULTI_DESC"}, {"begin": 11680, "end": 11694, "code": "569.5", "code_system": "ICD-9-CM", "description": "Abscess of intestine", "type": "MapType.MULTI_DESC"}, {"begin": 11865, "end": 11884, "code": "574.00", "code_system": "ICD-9-CM", "description": "Calculus of gallbladder with acute cholecystitis, without mention of obstruction", "type": "MapType.APPROX"}, {"begin": 12327, "end": 12335, "code": "787.91", "code_system": "ICD-9-CM", "description": "Diarrhea", "type": "MapType.APPROX"}, {"begin": 12609, "end": 12621, "code": "790.6", "code_system": "ICD-9-CM", "description": "Other abnormal blood chemistry", "type": "MapType.MULTI_DESC"}, {"begin": 13801, "end": 13815, "code": "543.9", "code_system": "ICD-9-CM", "description": "Other and unspecified diseases of appendix", "type": "MapType.APPROX"}, {"begin": 13823, "end": 13831, "code": "787.91", "code_system": "ICD-9-CM", "description": "Diarrhea", "type": "MapType.APPROX"}]}, {"note_id": 652441, "category": "Physician", "description": "Physician Resident Progress Note", "annotations": [{"begin": 74, "end": 97, "code": "574.50", "code_system": "ICD-9-CM", "description": "Calculus of bile duct without mention of cholecystitis, without mention of obstruction", "type": "MapType.APPROX"}, {"begin": 520, "end": 532, "code": "528.5", "code_system": "ICD-9-CM", "description": "Diseases of lips", "type": "MapType.EXACT"}, {"begin": 2856, "end": 2859, "code": "789.04", "code_system": "ICD-9-CM", "description": "Abdominal pain, left lower quadrant", "type": "MapType.EXACT"}, {"begin": 2861, "end": 2864, "code": "789.03", "code_system": "ICD-9-CM", "description": "Abdominal pain, right lower quadrant", "type": "MapType.EXACT"}, {"begin": 3803, "end": 3806, "code": "428.0", "code_system": "ICD-9-CM", "description": "Congestive heart failure, unspecified", "type": "MapType.MULTI"}, {"begin": 3815, "end": 3823, "code": "787.91", "code_system": "ICD-9-CM", "description": "Diarrhea", "type": "MapType.APPROX"}, {"begin": 3831, "end": 3850, "code": "574.20", "code_system": "ICD-9-CM", "description": "Calculus of gallbladder without mention of cholecystitis, without mention of obstruction", "type": "MapType.APPROX"}, {"begin": 4023, "end": 4028, "code": "780.60", "code_system": "ICD-9-CM", "description": "NO_DEF", "type": "MapType.APPROX"}, {"begin": 4044, "end": 4052, "code": "789.01", "code_system": "ICD-9-CM", "description": "Abdominal pain, right upper quadrant", "type": "MapType.EXACT"}, {"begin": 4057, "end": 4076, "code": "574.20", "code_system": "ICD-9-CM", "description": "Calculus of gallbladder without mention of cholecystitis, without mention of obstruction", "type": "MapType.APPROX"}, {"begin": 4211, "end": 4219, "code": "789.01", "code_system": "ICD-9-CM", "description": "Abdominal pain, right upper quadrant", "type": "MapType.EXACT"}, {"begin": 4260, "end": 4263, "code": "789.04", "code_system": "ICD-9-CM", "description": "Abdominal pain, left lower quadrant", "type": "MapType.EXACT"}, {"begin": 4264, "end": 4267, "code": "789.03", "code_system": "ICD-9-CM", "description": "Abdominal pain, right lower quadrant", "type": "MapType.EXACT"}, {"begin": 4422, "end": 4430, "code": "787.91", "code_system": "ICD-9-CM", "description": "Diarrhea", "type": "MapType.APPROX"}, {"begin": 4504, "end": 4512, "code": "787.91", "code_system": "ICD-9-CM", "description": "Diarrhea", "type": "MapType.APPROX"}, {"begin": 4517, "end": 4531, "code": "569.5", "code_system": "ICD-9-CM", "description": "Abscess of intestine", "type": "MapType.MULTI_DESC"}, {"begin": 4568, "end": 4576, "code": "787.91", "code_system": "ICD-9-CM", "description": "Diarrhea", "type": "MapType.APPROX"}, {"begin": 4655, "end": 4667, "code": "790.6", "code_system": "ICD-9-CM", "description": "Other abnormal blood chemistry", "type": "MapType.MULTI_DESC"}, {"begin": 4777, "end": 4785, "code": "787.91", "code_system": "ICD-9-CM", "description": "Diarrhea", "type": "MapType.APPROX"}]}, {"note_id": 652451, "category": "Physician", "description": "Physician Resident Progress Note", "annotations": [{"begin": 520, "end": 532, "code": "528.5", "code_system": "ICD-9-CM", "description": "Diseases of lips", "type": "MapType.EXACT"}, {"begin": 2872, "end": 2875, "code": "789.04", "code_system": "ICD-9-CM", "description": "Abdominal pain, left lower quadrant", "type": "MapType.EXACT"}, {"begin": 2877, "end": 2880, "code": "789.03", "code_system": "ICD-9-CM", "description": "Abdominal pain, right lower quadrant", "type": "MapType.EXACT"}, {"begin": 3819, "end": 3822, "code": "428.0", "code_system": "ICD-9-CM", "description": "Congestive heart failure, unspecified", "type": "MapType.MULTI"}, {"begin": 3831, "end": 3839, "code": "787.91", "code_system": "ICD-9-CM", "description": "Diarrhea", "type": "MapType.APPROX"}, {"begin": 3847, "end": 3866, "code": "574.20", "code_system": "ICD-9-CM", "description": "Calculus of gallbladder without mention of cholecystitis, without mention of obstruction", "type": "MapType.APPROX"}, {"begin": 4039, "end": 4044, "code": "780.60", "code_system": "ICD-9-CM", "description": "NO_DEF", "type": "MapType.APPROX"}, {"begin": 4060, "end": 4068, "code": "789.01", "code_system": "ICD-9-CM", "description": "Abdominal pain, right upper quadrant", "type": "MapType.EXACT"}, {"begin": 4073, "end": 4092, "code": "574.20", "code_system": "ICD-9-CM", "description": "Calculus of gallbladder without mention of cholecystitis, without mention of obstruction", "type": "MapType.APPROX"}, {"begin": 4227, "end": 4235, "code": "789.01", "code_system": "ICD-9-CM", "description": "Abdominal pain, right upper quadrant", "type": "MapType.EXACT"}, {"begin": 4276, "end": 4279, "code": "789.04", "code_system": "ICD-9-CM", "description": "Abdominal pain, left lower quadrant", "type": "MapType.EXACT"}, {"begin": 4280, "end": 4283, "code": "789.03", "code_system": "ICD-9-CM", "description": "Abdominal pain, right lower quadrant", "type": "MapType.EXACT"}, {"begin": 4438, "end": 4446, "code": "787.91", "code_system": "ICD-9-CM", "description": "Diarrhea", "type": "MapType.APPROX"}, {"begin": 4520, "end": 4528, "code": "787.91", "code_system": "ICD-9-CM", "description": "Diarrhea", "type": "MapType.APPROX"}, {"begin": 4533, "end": 4547, "code": "569.5", "code_system": "ICD-9-CM", "description": "Abscess of intestine", "type": "MapType.MULTI_DESC"}, {"begin": 4584, "end": 4592, "code": "787.91", "code_system": "ICD-9-CM", "description": "Diarrhea", "type": "MapType.APPROX"}, {"begin": 4671, "end": 4683, "code": "790.6", "code_system": "ICD-9-CM", "description": "Other abnormal blood chemistry", "type": "MapType.MULTI_DESC"}, {"begin": 4793, "end": 4801, "code": "787.91", "code_system": "ICD-9-CM", "description": "Diarrhea", "type": "MapType.APPROX"}]}, {"note_id": 1054634, "category": "Radiology", "description": "CT ABDOMEN W/CONTRAST", "annotations": [{"begin": 25, "end": 68, "code": "74170", "code_system": "CPT", "description": "Computed tomography, abdomen; without contrast material, followed by contrast material(s) and further sections", "type": "Human"}, {"begin": 181, "end": 187, "code": "780.60", "code_system": "ICD-9-CM", "description": "NO_DEF", "type": "MapType.APPROX"}, {"begin": 192, "end": 200, "code": "787.91", "code_system": "ICD-9-CM", "description": "Diarrhea", "type": "MapType.APPROX"}, {"begin": 224, "end": 244, "code": "574.20", "code_system": "ICD-9-CM", "description": "Calculus of gallbladder without mention of cholecystitis, without mention of obstruction", "type": "MapType.APPROX"}, {"begin": 426, "end": 434, "code": "787.91", "code_system": "ICD-9-CM", "description": "Diarrhea", "type": "MapType.APPROX"}, {"begin": 439, "end": 445, "code": "780.60", "code_system": "ICD-9-CM", "description": "NO_DEF", "type": "MapType.APPROX"}, {"begin": 544, "end": 550, "code": "780.60", "code_system": "ICD-9-CM", "description": "NO_DEF", "type": "MapType.APPROX"}, {"begin": 555, "end": 563, "code": "787.91", "code_system": "ICD-9-CM", "description": "Diarrhea", "type": "MapType.APPROX"}, {"begin": 814, "end": 822, "code": "787.91", "code_system": "ICD-9-CM", "description": "Diarrhea", "type": "MapType.APPROX"}, {"begin": 824, "end": 830, "code": "780.60", "code_system": "ICD-9-CM", "description": "NO_DEF", "type": "MapType.APPROX"}, {"begin": 1168, "end": 1185, "code": "511.1", "code_system": "ICD-9-CM", "description": "Pleurisy with effusion, with mention of a bacterial cause other than tuberculosis", "type": "MapType.MULTI_DESC"}, {"begin": 1203, "end": 1214, "code": "518.0", "code_system": "ICD-9-CM", "description": "Pulmonary collapse", "type": "MapType.APPROX"}, {"begin": 1353, "end": 1384, "code": "576.9", "code_system": "ICD-9-CM", "description": "Unspecified disorder of biliary tract", "type": "MapType.EXACT"}, {"begin": 2200, "end": 2211, "code": "562.11", "code_system": "ICD-9-CM", "description": "Diverticulitis of colon without mention of hemorrhage", "type": "MapType.APPROX"}, {"begin": 3049, "end": 3080, "code": "722.52", "code_system": "ICD-9-CM", "description": "Degeneration of lumbar or lumbosacral intervertebral disc", "type": "MapType.APPROX"}, {"begin": 3354, "end": 3360, "code": "780.60", "code_system": "ICD-9-CM", "description": "NO_DEF", "type": "MapType.APPROX"}, {"begin": 3365, "end": 3373, "code": "787.91", "code_system": "ICD-9-CM", "description": "Diarrhea", "type": "MapType.APPROX"}, {"begin": 3397, "end": 3417, "code": "574.20", "code_system": "ICD-9-CM", "description": "Calculus of gallbladder without mention of cholecystitis, without mention of obstruction", "type": "MapType.APPROX"}, {"begin": 3803, "end": 3814, "code": "562.11", "code_system": "ICD-9-CM", "description": "Diverticulitis of colon without mention of hemorrhage", "type": "MapType.APPROX"}, {"begin": 3877, "end": 3891, "code": "569.5", "code_system": "ICD-9-CM", "description": "Abscess of intestine", "type": "MapType.MULTI_DESC"}, {"begin": 4101, "end": 4112, "code": "576.8", "code_system": "ICD-9-CM", "description": "Other specified disorders of biliary tract", "type": "MapType.APPROX"}, {"begin": 4153, "end": 4185, "code": "576.9", "code_system": "ICD-9-CM", "description": "Unspecified disorder of biliary tract", "type": "MapType.EXACT"}, {"begin": 4197, "end": 4225, "code": "577.8", "code_system": "ICD-9-CM", "description": "Other specified diseases of pancreas", "type": "MapType.APPROX"}]}, {"note_id": 652374, "category": "Physician", "description": "Physician Attending Admission Note - MICU", "annotations": [{"begin": 18, "end": 38, "code": "770.89", "code_system": "ICD-9-CM", "description": "Other respiratory problems after birth", "type": "MapType.MULTI_DESC"}, {"begin": 331, "end": 342, "code": "041.6", "code_system": "ICD-9-CM", "description": "Proteus (mirabilis) (morganii) infection in conditions classified elsewhere and of unspecified site", "type": "MapType.EXACT"}, {"begin": 350, "end": 371, "code": "780.97", "code_system": "ICD-9-CM", "description": "Altered mental status", "type": "MapType.APPROX"}, {"begin": 468, "end": 478, "code": "518.4", "code_system": "ICD-9-CM", "description": "Acute edema of lung, unspecified", "type": "MapType.EXACT"}, {"begin": 1126, "end": 1138, "code": "528.5", "code_system": "ICD-9-CM", "description": "Diseases of lips", "type": "MapType.EXACT"}, {"begin": 1524, "end": 1527, "code": "401.9", "code_system": "ICD-9-CM", "description": "Unspecified essential hypertension", "type": "MapType.MULTI_DESC"}, {"begin": 1531, "end": 1540, "code": "716.20", "code_system": "ICD-9-CM", "description": "Allergic arthritis, site unspecified", "type": "MapType.APPROX"}, {"begin": 1544, "end": 1550, "code": "285.9", "code_system": "ICD-9-CM", "description": "Anemia, unspecified", "type": "Human"}, {"begin": 1554, "end": 1566, "code": "273.3", "code_system": "ICD-9-CM", "description": "Macroglobulinemia", "type": "MapType.APPROX"}, {"begin": 1804, "end": 1811, "code": "780.79", "code_system": "ICD-9-CM", "description": "Other malaise and fatigue", "type": "MapType.APPROX"}, {"begin": 1813, "end": 1818, "code": "780.60", "code_system": "ICD-9-CM", "description": "NO_DEF", "type": "MapType.APPROX"}, {"begin": 1870, "end": 1880, "code": "786.50", "code_system": "ICD-9-CM", "description": "Unspecified chest pain", "type": "MapType.EXACT"}, {"begin": 1882, "end": 1893, "code": "786.06", "code_system": "ICD-9-CM", "description": "Tachypnea", "type": "MapType.EXACT"}, {"begin": 1895, "end": 1904, "code": "786.02", "code_system": "ICD-9-CM", "description": "Orthopnea", "type": "MapType.EXACT"}, {"begin": 1921, "end": 1928, "code": "786.09", "code_system": "ICD-9-CM", "description": "Other dyspnea and respiratory abnormality", "type": "MapType.APPROX"}, {"begin": 1941, "end": 1947, "code": "786.07", "code_system": "ICD-9-CM", "description": "Wheezing", "type": "MapType.EXACT"}, {"begin": 2021, "end": 2027, "code": "285.9", "code_system": "ICD-9-CM", "description": "Anemia, unspecified", "type": "Human"}, {"begin": 3908, "end": 3929, "code": "786.09", "code_system": "ICD-9-CM", "description": "Other dyspnea and respiratory abnormality", "type": "MapType.MULTI_DESC"}, {"begin": 4884, "end": 4898, "code": "574.00", "code_system": "ICD-9-CM", "description": "Calculus of gallbladder with acute cholecystitis, without mention of obstruction", "type": "MapType.APPROX"}]}, {"note_id": 1054193, "category": "Radiology", "description": "LIVER OR GALLBLADDER US (SINGLE ORGAN)", "annotations": [{"begin": 25, "end": 48, "code": "76700", "code_system": "CPT", "description": "Ultrasound, abdominal, real time with image documentation; complete", "type": "Human"}, {"begin": 342, "end": 361, "code": "574.20", "code_system": "ICD-9-CM", "description": "Calculus of gallbladder without mention of cholecystitis, without mention of obstruction", "type": "MapType.APPROX"}, {"begin": 401, "end": 406, "code": "780.60", "code_system": "ICD-9-CM", "description": "NO_DEF", "type": "MapType.APPROX"}, {"begin": 676, "end": 695, "code": "574.20", "code_system": "ICD-9-CM", "description": "Calculus of gallbladder without mention of cholecystitis, without mention of obstruction", "type": "MapType.APPROX"}, {"begin": 993, "end": 1012, "code": "574.20", "code_system": "ICD-9-CM", "description": "Calculus of gallbladder without mention of cholecystitis, without mention of obstruction", "type": "MapType.APPROX"}, {"begin": 1018, "end": 1023, "code": "780.60", "code_system": "ICD-9-CM", "description": "NO_DEF", "type": "MapType.APPROX"}, {"begin": 1029, "end": 1043, "code": "789.00", "code_system": "ICD-9-CM", "description": "Abdominal pain, unspecified site", "type": "MapType.APPROX"}, {"begin": 1623, "end": 1642, "code": "574.00", "code_system": "ICD-9-CM", "description": "Calculus of gallbladder with acute cholecystitis, without mention of obstruction", "type": "MapType.APPROX"}, {"begin": 1738, "end": 1752, "code": "997.41", "code_system": "ICD-9-CM", "description": "NO_DEF", "type": "MapType.EXACT"}]}, {"note_id": 1054550, "category": "Radiology", "description": "ERCP BILIARY&PANCREAS BY GI UNIT", "annotations": [{"begin": 25, "end": 57, "code": "74160", "code_system": "CPT", "description": "Computed tomography, abdomen; with contrast material(s)", "type": "Human"}, {"begin": 205, "end": 225, "code": "574.20", "code_system": "ICD-9-CM", "description": "Calculus of gallbladder without mention of cholecystitis, without mention of obstruction", "type": "MapType.APPROX"}, {"begin": 383, "end": 388, "code": "780.60", "code_system": "ICD-9-CM", "description": "NO_DEF", "type": "MapType.APPROX"}, {"begin": 823, "end": 842, "code": "576.2", "code_system": "ICD-9-CM", "description": "Obstruction of bile duct", "type": "MapType.EXACT"}, {"begin": 844, "end": 858, "code": "789.00", "code_system": "ICD-9-CM", "description": "Abdominal pain, unspecified site", "type": "MapType.APPROX"}, {"begin": 864, "end": 869, "code": "780.60", "code_system": "ICD-9-CM", "description": "NO_DEF", "type": "MapType.APPROX"}]}, {"note_id": 1054551, "category": "Radiology", "description": "ERCP BILIARY&PANCREAS BY GI UNIT", "annotations": [{"begin": 129, "end": 161, "code": "74160", "code_system": "CPT", "description": "Computed tomography, abdomen; with contrast material(s)", "type": "Human"}, {"begin": 309, "end": 329, "code": "574.20", "code_system": "ICD-9-CM", "description": "Calculus of gallbladder without mention of cholecystitis, without mention of obstruction", "type": "MapType.APPROX"}, {"begin": 457, "end": 482, "code": "789.00", "code_system": "ICD-9-CM", "description": "Abdominal pain, unspecified site", "type": "MapType.APPROX"}, {"begin": 487, "end": 492, "code": "780.60", "code_system": "ICD-9-CM", "description": "NO_DEF", "type": "MapType.APPROX"}]}, {"note_id": 652249, "category": "Physician", "description": "Physician Attending Admission Note - MICU", "annotations": [{"begin": 18, "end": 24, "code": "995.91", "code_system": "ICD-9-CM", "description": "Sepsis", "type": "MapType.MULTI_DESC"}, {"begin": 303, "end": 311, "code": "787.91", "code_system": "ICD-9-CM", "description": "Diarrhea", "type": "MapType.APPROX"}, {"begin": 404, "end": 412, "code": "787.91", "code_system": "ICD-9-CM", "description": "Diarrhea", "type": "MapType.APPROX"}, {"begin": 1081, "end": 1093, "code": "528.5", "code_system": "ICD-9-CM", "description": "Diseases of lips", "type": "MapType.EXACT"}, {"begin": 1281, "end": 1284, "code": "428.0", "code_system": "ICD-9-CM", "description": "Congestive heart failure, unspecified", "type": "MapType.MULTI"}, {"begin": 5801, "end": 5820, "code": "574.00", "code_system": "ICD-9-CM", "description": "Calculus of gallbladder with acute cholecystitis, without mention of obstruction", "type": "MapType.APPROX"}, {"begin": 5822, "end": 5830, "code": "787.91", "code_system": "ICD-9-CM", "description": "Diarrhea", "type": "MapType.APPROX"}]}]}
